[
{
    "pk": null,
    "model": "allaccess.provider",
    "fields": {
        "name": "facebook",
        "authorization_url": "https://www.facebook.com/v2.8/dialog/oauth",
        "access_token_url": "https://graph.facebook.com/v2.8/oauth/access_token",
        "request_token_url": "",
        "profile_url": "https://graph.facebook.com/v2.8/me"
    }
},
{
    "pk": null,
    "model": "allaccess.provider",
    "fields": {
        "name": "twitter",
        "authorization_url": "https://api.twitter.com/oauth/authenticate",
        "access_token_url": "https://api.twitter.com/oauth/access_token",
        "request_token_url": "https://api.twitter.com/oauth/request_token",
        "profile_url": "https://api.twitter.com/1.1/account/verify_credentials.json"
    }
},
{
    "pk": null,
    "model": "allaccess.provider",
    "fields": {
        "name": "google",
        "authorization_url": "https://accounts.google.com/o/oauth2/auth",
        "access_token_url": "https://accounts.google.com/o/oauth2/token",
        "request_token_url": "",
        "profile_url": "https://www.googleapis.com/oauth2/v1/userinfo"
    }
},
{
    "pk": null,
    "model": "allaccess.provider",
    "fields": {
        "name": "microsoft",
        "authorization_url": "https://login.live.com/oauth20_authorize.srf",
        "access_token_url": "https://login.live.com/oauth20_token.srf",
        "request_token_url": "",
        "profile_url": "https://apis.live.net/v5.0/me"
    }
},
{
    "pk": null,
    "model": "allaccess.provider",
    "fields": {
        "name": "github",
        "authorization_url": "https://github.com/login/oauth/authorize",
        "access_token_url": "https://github.com/login/oauth/access_token",
        "request_token_url": "",
        "profile_url": "https://api.github.com/user"
    }
},
{
    "pk": null,
    "model": "allaccess.provider",
    "fields": {
        "name": "bitbucket",
        "authorization_url": "https://bitbucket.org/api/1.0/oauth/authenticate/",
        "access_token_url": "https://bitbucket.org/api/1.0/oauth/access_token/",
        "request_token_url": "https://bitbucket.org/api/1.0/oauth/request_token/",
        "profile_url": "https://api.bitbucket.org/1.0/user/"
    }
}
]
